python_import_analyzer/__init__.py
python_import_analyzer/dependency_analyzer.py
python_import_analyzer/dependency_dashboard.py
python_import_analyzer/assets/.keep
python_import_analyzer/assets/README.md
python_import_analyzer-0.1.3.dist-info/licenses/LICENSE
python_import_analyzer-0.1.3.dist-info/METADATA
python_import_analyzer-0.1.3.dist-info/WHEEL
python_import_analyzer-0.1.3.dist-info/entry_points.txt
python_import_analyzer-0.1.3.dist-info/top_level.txt
python_import_analyzer-0.1.3.dist-info/RECORD
