Metadata-Version: 2.4
Name: python-import-analyzer
Version: 0.1.3
Summary: A tool for visualizing and analyzing import dependencies in Python projects
Home-page: https://github.com/sieverett/Python-Import-Analyzer
Author: Weavery
Author-email: silas@eweavery.ai
Project-URL: Bug Tracker, https://github.com/sieverett/Python-Import-Analyzer/issues
Project-URL: Documentation, https://github.com/sieverett/Python-Import-Analyzer/blob/main/README.md
Project-URL: Source Code, https://github.com/sieverett/Python-Import-Analyzer
Classifier: Programming Language :: Python :: 3
Classifier: License :: OSI Approved :: MIT License
Classifier: Operating System :: OS Independent
Requires-Python: >=3.6
License-File: LICENSE
Requires-Dist: networkx
Requires-Dist: matplotlib
Requires-Dist: plotly
Requires-Dist: dash>=2.0.0
Requires-Dist: dash-cytoscape
Requires-Dist: pandas
Dynamic: author
Dynamic: author-email
Dynamic: classifier
Dynamic: description
Dynamic: description-content-type
Dynamic: home-page
Dynamic: license-file
Dynamic: project-url
Dynamic: requires-dist
Dynamic: requires-python
Dynamic: summary
